tsmetrics/__init__.py
tsmetrics/tsmetrics.py
tsmetrics-0.1.0.dist-info/DESCRIPTION.rst
tsmetrics-0.1.0.dist-info/METADATA
tsmetrics-0.1.0.dist-info/RECORD
tsmetrics-0.1.0.dist-info/WHEEL
tsmetrics-0.1.0.dist-info/metadata.json
tsmetrics-0.1.0.dist-info/top_level.txt
