Metadata-Version: 2.0
Name: tsmetrics
Version: 0.1.0
Summary: Evaluation metrics for time series analysis
Home-page: https://github.com/pranavbahl2308/tsmetrics
Author: Pranav Bahl
Author-email: pranavshekharbahl@gmail.com
License: MIT
Download-URL: https://github.com/pranavbahl2308/tsmetrics
Keywords: python,timeseries,evaluation,metrics,rmse,mse,mae,mape,mase,smape,sse,smse,nmse
Platform: UNKNOWN
Requires-Dist: numpy
